mh_operator/__init__.py
mh_operator/__main__.py
mh_operator/version.py
mh_operator/SDK/AGaugeApp.pyi
mh_operator/SDK/BasicTypes.pyi
mh_operator/SDK/Biochemistry.pyi
mh_operator/SDK/CommonAlgorithms.pyi
mh_operator/SDK/CompositionCalculatorEngine.pyi
mh_operator/SDK/CompositionDB.pyi
mh_operator/SDK/CompoundFilters.pyi
mh_operator/SDK/CorrelationNormalizationEngine3.pyi
mh_operator/SDK/DataFitX3.pyi
mh_operator/SDK/Definitions.pyi
mh_operator/SDK/GenieIntegrator.pyi
mh_operator/SDK/IWshRuntimeLibrary.pyi
mh_operator/SDK/IsotopePatternCalculator.pyi
mh_operator/SDK/Mathematics.pyi
mh_operator/SDK/Mfe.pyi
mh_operator/SDK/MhdFile.pyi
mh_operator/SDK/OpenLABTranslator.pyi
mh_operator/SDK/PersistanceFiles.pyi
mh_operator/SDK/Util.pyi
mh_operator/SDK/XamlGeneratedNamespace.pyi
mh_operator/SDK/__init__.pyi
mh_operator/SDK/Agilent/__init__.pyi
mh_operator/SDK/Agilent/MSAcquisition/CustomizeFolder.pyi
mh_operator/SDK/Agilent/MSAcquisition/SampleInfoRW.pyi
mh_operator/SDK/Agilent/MSAcquisition/__init__.pyi
mh_operator/SDK/Agilent/MSAcquisition/HashSignature/Properties.pyi
mh_operator/SDK/Agilent/MSAcquisition/HashSignature/__init__.pyi
mh_operator/SDK/Agilent/MassHunter/ReportCommon.pyi
mh_operator/SDK/Agilent/MassHunter/__init__.pyi
mh_operator/SDK/Agilent/MassHunter/Quantitative/CalibrationCurveAtAGlance.pyi
mh_operator/SDK/Agilent/MassHunter/Quantitative/ConvertSamples.pyi
mh_operator/SDK/Agilent/MassHunter/Quantitative/ErrorWindow.pyi
mh_operator/SDK/Agilent/MassHunter/Quantitative/HeatMap.pyi
mh_operator/SDK/Agilent/MassHunter/Quantitative/PlotControl.pyi
mh_operator/SDK/Agilent/MassHunter/Quantitative/PlotControl3D.pyi
mh_operator/SDK/Agilent/MassHunter/Quantitative/QuantAppServices.pyi
mh_operator/SDK/Agilent/MassHunter/Quantitative/Screening.pyi
mh_operator/SDK/Agilent/MassHunter/Quantitative/SetupDesktopIconsWPF.pyi
mh_operator/SDK/Agilent/MassHunter/Quantitative/UIModel.pyi
mh_operator/SDK/Agilent/MassHunter/Quantitative/__init__.pyi
mh_operator-0.2.3.dist-info/METADATA
mh_operator-0.2.3.dist-info/WHEEL
mh_operator-0.2.3.dist-info/entry_points.txt
mh_operator-0.2.3.dist-info/licenses/LICENSE
mh_operator-0.2.3.dist-info/RECORD
